metool_mcp/__init__.py
metool_mcp/server.py
metool_mcp-0.2.3.dist-info/METADATA
metool_mcp-0.2.3.dist-info/WHEEL
metool_mcp-0.2.3.dist-info/entry_points.txt
metool_mcp-0.2.3.dist-info/RECORD
