Metadata-Version: 2.4
Name: metool-mcp
Version: 0.2.3
Summary: MCP server for metool - a shell environment incubator
Project-URL: Homepage, https://github.com/mbailey/metool
Project-URL: Repository, https://github.com/mbailey/metool
Project-URL: Issues, https://github.com/mbailey/metool/issues
Author-email: Mike Bailey <mike@m.fail>
License: MIT
Keywords: ai,git,llm,management,mcp,metool,repository,shell
Classifier: Development Status :: 3 - Alpha
Classifier: Intended Audience :: Developers
Classifier: License :: OSI Approved :: MIT License
Classifier: Programming Language :: Python :: 3
Classifier: Programming Language :: Python :: 3.10
Classifier: Programming Language :: Python :: 3.11
Classifier: Programming Language :: Python :: 3.12
Classifier: Topic :: Software Development :: Version Control :: Git
Classifier: Topic :: System :: Shells
Classifier: Topic :: Utilities
Requires-Python: >=3.10
Requires-Dist: fastmcp>=2.0.0
